configmate_plugins/toml_parser/__init__.py
configmate_plugins/toml_parser/toml_parser.py
configmate_tomlparser-0.1.1.dist-info/METADATA
configmate_tomlparser-0.1.1.dist-info/WHEEL
configmate_tomlparser-0.1.1.dist-info/RECORD
